indy_dev_tools/__init__.py
indy_dev_tools/commands/__init__.py
indy_dev_tools/commands/config.py
indy_dev_tools/commands/descriptions.py
indy_dev_tools/commands/hashtags.py
indy_dev_tools/commands/playground.py
indy_dev_tools/commands/references.py
indy_dev_tools/commands/script.py
indy_dev_tools/commands/simple_prompt_system.py
indy_dev_tools/commands/thumbnails.py
indy_dev_tools/commands/titles.py
indy_dev_tools/commands/youtube.py
indy_dev_tools/main.py
indy_dev_tools/models.py
indy_dev_tools/modules/compose_description.py
indy_dev_tools/modules/compose_hashtags.py
indy_dev_tools/modules/compose_thumbnail.py
indy_dev_tools/modules/compose_title.py
indy_dev_tools/modules/create_description.py
indy_dev_tools/modules/create_formatted_references.py
indy_dev_tools/modules/create_hashtags.py
indy_dev_tools/modules/create_research.py
indy_dev_tools/modules/create_thumbnail.py
indy_dev_tools/modules/create_thumbnail_prompt.py
indy_dev_tools/modules/create_title.py
indy_dev_tools/modules/create_transcription.py
indy_dev_tools/modules/dict_util.py
indy_dev_tools/modules/file_util.py
indy_dev_tools/modules/generate_metadata_flow.py
indy_dev_tools/modules/idt_config.py
indy_dev_tools/modules/llm.py
indy_dev_tools/modules/prompts.py
indy_dev_tools/modules/resize_image.py
indy_dev_tools/modules/sps_get.py
indy_dev_tools/modules/sps_list.py
indy_dev_tools/modules/sps_prompt.py
indydevtools-0.2.6.dist-info/METADATA
indydevtools-0.2.6.dist-info/WHEEL
indydevtools-0.2.6.dist-info/entry_points.txt
indydevtools-0.2.6.dist-info/RECORD
