Metadata-Version: 2.1
Name: indydevtools
Version: 0.2.6
Summary: An opinionated Agentic Engineering toolbox powered by LLM Agents to solve problems autonomously.
Home-page: https://github.com/disler/indydevtools
License: MIT
Author: IndyDevDan
Author-email: agentic@indydevdan.com
Requires-Python: >=3.10,<4.0
Classifier: License :: OSI Approved :: MIT License
Classifier: Programming Language :: Python :: 3
Classifier: Programming Language :: Python :: 3.10
Classifier: Programming Language :: Python :: 3.11
Requires-Dist: exa-py (>=1.0.8,<2.0.0)
Requires-Dist: faster-whisper (>=0.10.0,<0.11.0)
Requires-Dist: inquirer (>=3.2.3,<4.0.0)
Requires-Dist: openai (>=1.11.0,<2.0.0)
Requires-Dist: pillow (>=10.2.0,<11.0.0)
Requires-Dist: platformdirs (>=4.2.0,<5.0.0)
Requires-Dist: pydantic (>=2.6.0,<3.0.0)
Requires-Dist: python-dotenv (>=1.0.1,<2.0.0)
Requires-Dist: pyyaml (>=6.0.1,<7.0.0)
Requires-Dist: requests (>=2.31.0,<3.0.0)
Requires-Dist: typer (>=0.9.0,<0.10.0)
Project-URL: Repository, https://github.com/disler/indydevtools
